{"version": "https://jsonfeed.org/version/1", "title": "Chris Jennings - his Photos", "home_page_url": "https://photos.chrisjennings.net/", "feed_url": "https://photos.chrisjennings.net/feed_json_updated.json", "description": "My personal photo site", "icon": null, "authors": [], "language": "en", "items": [{"id": "https://photos.chrisjennings.net/1979/ant-drawing/", "url": "https://photos.chrisjennings.net/1979/ant-drawing/", "title": "Ant Drawing", "content_html": "<p><img alt=\"Ant drawing - Chalk on Rock, Ardpatrick, 1979\" src=\"https://live.staticflickr.com/65535/49849911156_72e25fce55_3k.jpg\"></p>\n<p>Scanned from a 5x4 black and white negat...</p>", "image": "https://photos.chrisjennings.net/assets/images/social/photos/Ant drawing.png", "date_modified": "2025-09-24T14:33:04+00:00", "authors": [], "tags": null}, {"id": "https://photos.chrisjennings.net/1982/approaching-the-island-of-tanera-m%C3%B3re/", "url": "https://photos.chrisjennings.net/1982/approaching-the-island-of-tanera-m%C3%B3re/", "title": "Approaching the island of Tanera M\u00f3re", "content_html": "<p><img alt=\"On board the ketch &quot;Deli&quot;\" src=\"https://live.staticflickr.com/65535/49882953441_b519ec618d_h_d.jpg\"></p>\n<p>35mm Film positive Ektachrome. Maybe 1980</p>", "image": "https://photos.chrisjennings.net/assets/images/social/photos/Approaching the island of Tanera M\u00f3re.png", "date_modified": "2025-09-24T14:33:04+00:00", "authors": [], "tags": null}, {"id": "https://photos.chrisjennings.net/2025/arch-under-the-old-gasworks-bridge-over-the-thames-at-oxford/", "url": "https://photos.chrisjennings.net/2025/arch-under-the-old-gasworks-bridge-over-the-thames-at-oxford/", "title": "Arch under the Old Gasworks Bridge over the Thames at Oxford", "content_html": "<p><img alt=\"Arch under the Old Gasworks Bridge\" src=\"https://live.staticflickr.com/65535/54388970730_b8ed0fc20e_h_d.jpg\"></p>", "image": "https://photos.chrisjennings.net/assets/images/social/photos/Arch under the Old Gasworks Bridge.png", "date_modified": "2025-09-24T14:33:04+00:00", "authors": [], "tags": null}, {"id": "https://photos.chrisjennings.net/2025/autumn-at-the-arboretum/", "url": "https://photos.chrisjennings.net/2025/autumn-at-the-arboretum/", "title": "Autumn at the Arboretum", "content_html": "<p><img alt=\"Autumn at the Arboretum\" src=\"https://live.staticflickr.com/65535/50528542197_6a65fc6264_h_d.jpg\"></p>", "image": "https://photos.chrisjennings.net/assets/images/social/photos/Autumn at the Arboretum.png", "date_modified": "2025-09-24T14:33:04+00:00", "authors": [], "tags": null}, {"id": "https://photos.chrisjennings.net/2025/bracken/", "url": "https://photos.chrisjennings.net/2025/bracken/", "title": "Bracken", "content_html": "<p><img alt=\"Amongst the grasses and pathways\" src=\"https://www.flickr.com/photo_download.gne?size=h&amp;id=54590610540&amp;secret=9018390bc3\"></p>", "image": "https://photos.chrisjennings.net/assets/images/social/photos/Bracken.png", "date_modified": "2025-09-24T14:33:04+00:00", "authors": [], "tags": null}, {"id": "https://photos.chrisjennings.net/2020/bread-wheat/", "url": "https://photos.chrisjennings.net/2020/bread-wheat/", "title": "Bread Wheat", "content_html": "<p><img alt=\"Bread Wheat Field, Clifton Hampden\" src=\"https://live.staticflickr.com/65535/54402821404_b183a0634f_h_d.jpg\"></p>", "image": "https://photos.chrisjennings.net/assets/images/social/photos/Bread Wheat.png", "date_modified": "2025-09-24T14:33:04+00:00", "authors": [], "tags": null}, {"id": "https://photos.chrisjennings.net/1979/crab-drawing-on-rock/", "url": "https://photos.chrisjennings.net/1979/crab-drawing-on-rock/", "title": "Crab drawing on rock", "content_html": "<p><img alt=\"Crab drawing - Chalk on rock, Ardpatrick, 1979\" src=\"https://live.staticflickr.com/65535/49849909056_e3e6d467af_h_d.jpg\"></p>\n<p>Scanned from a 5x4 black and white ne...</p>", "image": "https://photos.chrisjennings.net/assets/images/social/photos/Crab drawing.png", "date_modified": "2025-09-24T14:33:04+00:00", "authors": [], "tags": null}, {"id": "https://photos.chrisjennings.net/1981/deli-with-her-mainsail-up/", "url": "https://photos.chrisjennings.net/1981/deli-with-her-mainsail-up/", "title": "Deli with her mainsail up", "content_html": "<p><img alt=\"Sailing in the Hebrides\" src=\"https://live.staticflickr.com/65535/49883259417_b652e6fd92_o.jpg\"></p>\n<p>35mm Film positive Ektachrome. Maybe 1980. Alistair on the bow...</p>", "image": "https://photos.chrisjennings.net/assets/images/social/photos/Deli with her mainsail up.png", "date_modified": "2025-09-24T14:33:04+00:00", "authors": [], "tags": null}, {"id": "https://photos.chrisjennings.net/2022/door-at-dorchester-abbey/", "url": "https://photos.chrisjennings.net/2022/door-at-dorchester-abbey/", "title": "Door at Dorchester Abbey", "content_html": "<p><img alt=\"Door at Dorchester Abbey, Oxfordshire\" src=\"https://live.staticflickr.com/65535/52330110370_e50cae8e08_h_d.jpg\"></p>", "image": "https://photos.chrisjennings.net/assets/images/social/photos/Door at Dorchester Abbey.png", "date_modified": "2025-09-24T14:33:04+00:00", "authors": [], "tags": null}, {"id": "https://photos.chrisjennings.net/1979/eilean-m%C3%B2r-maccormaig-isles/", "url": "https://photos.chrisjennings.net/1979/eilean-m%C3%B2r-maccormaig-isles/", "title": "Eilean M\u00f2r, MacCormaig Isles", "content_html": "<hr>\n<p><img alt=\"Eilean M\u00f2r, MacCormaig Isles\" src=\"https://live.staticflickr.com/65535/49818057896_de9724e446_h_d.jpg\"></p>\n<p>Deli at the MacCormaigs,  Taken circa July 1979</p>", "image": "https://photos.chrisjennings.net/assets/images/social/photos/Eilean M\u00f2r, MacCormaig Isles.png", "date_modified": "2025-09-24T14:33:04+00:00", "authors": [], "tags": null}, {"id": "https://photos.chrisjennings.net/2025/elephant-in-sri-lanka/", "url": "https://photos.chrisjennings.net/2025/elephant-in-sri-lanka/", "title": "Elephant in Sri Lanka", "content_html": "<p><img alt=\"Sri Lankan Elephant\" src=\"https://live.staticflickr.com/65535/54319104381_12964129fd_h_d.jpg\"></p>", "image": "https://photos.chrisjennings.net/assets/images/social/photos/Elephant in Sri Lanka.png", "date_modified": "2025-09-24T14:33:04+00:00", "authors": [], "tags": null}, {"id": "https://photos.chrisjennings.net/1979/feather-drawing/", "url": "https://photos.chrisjennings.net/1979/feather-drawing/", "title": "Feather drawing", "content_html": "<p><img alt=\"Feather drawing on rock with chalk\" src=\"https://live.staticflickr.com/65535/49849374288_f3542d4b21_k_d.jpg\"></p>\n<p>Scanned from a 5x4 black and white negative. Ilfor...</p>", "image": "https://photos.chrisjennings.net/assets/images/social/photos/Feather drawing.png", "date_modified": "2025-09-24T14:33:04+00:00", "authors": [], "tags": null}, {"id": "https://photos.chrisjennings.net/1979/fish-tail-drawn-with-chalk/", "url": "https://photos.chrisjennings.net/1979/fish-tail-drawn-with-chalk/", "title": "Fish tail drawn with Chalk", "content_html": "<p><img alt=\"Fish tail drawn with Chalk on shore rocks, Ardpatrick 1979\" src=\"https://live.staticflickr.com/65535/49850218742_594553a1f2_3k.jpg\"></p>\n<p>Scanned from a 5x4 black a...</p>", "image": "https://photos.chrisjennings.net/assets/images/social/photos/Fish tail drawn with Chalk.png", "date_modified": "2025-09-24T14:33:04+00:00", "authors": [], "tags": null}, {"id": "https://photos.chrisjennings.net/2021/fractal-tree/", "url": "https://photos.chrisjennings.net/2021/fractal-tree/", "title": "Fractal Tree", "content_html": "<p><img alt=\"Tree with no life, Wytham, Oxfordshire\" src=\"https://live.staticflickr.com/65535/51419090522_05ce2a3124_h_d.jpg\"></p>", "image": "https://photos.chrisjennings.net/assets/images/social/photos/Fractal Tree.png", "date_modified": "2025-09-24T14:33:04+00:00", "authors": [], "tags": null}, {"id": "https://photos.chrisjennings.net/2022/gate-no-longer-fits/", "url": "https://photos.chrisjennings.net/2022/gate-no-longer-fits/", "title": "Gate No Longer Fits", "content_html": "<p><img alt=\"Dampness and weather and soft ground\" src=\"https://live.staticflickr.com/65535/51808813035_8298bd7a51_h_d.jpg\"></p>\n<p>Took this photo on Boars Hill on a damp and mist...</p>", "image": "https://photos.chrisjennings.net/assets/images/social/photos/Gate No Longer Fits.png", "date_modified": "2025-09-24T14:33:04+00:00", "authors": [], "tags": null}, {"id": "https://photos.chrisjennings.net/2020/gate-at-minster-lovell/", "url": "https://photos.chrisjennings.net/2020/gate-at-minster-lovell/", "title": "Gate at Minster Lovell", "content_html": "<p><img alt=\"Kissing gate\" src=\"https://live.staticflickr.com/65535/50361096666_91e6e49c35_h_d.jpg\"></p>\n<p>Taken with Rollei 35</p>", "image": "https://photos.chrisjennings.net/assets/images/social/photos/Gate at Minster Lovell.png", "date_modified": "2025-09-24T14:33:04+00:00", "authors": [], "tags": null}, {"id": "https://photos.chrisjennings.net/2020/gate-by-the-river/", "url": "https://photos.chrisjennings.net/2020/gate-by-the-river/", "title": "Gate by the river", "content_html": "<p><img alt=\"Gate by the river Thames, Near to Day's Lock\" src=\"https://live.staticflickr.com/65535/50361247057_3a45da8d06_h_d.jpg\"></p>\n<p>Taken with Rollei 35</p>", "image": "https://photos.chrisjennings.net/assets/images/social/photos/Gate by the river.png", "date_modified": "2025-09-24T14:33:04+00:00", "authors": [], "tags": null}, {"id": "https://photos.chrisjennings.net/2025/godstow-bridge-on-the-thames/", "url": "https://photos.chrisjennings.net/2025/godstow-bridge-on-the-thames/", "title": "Godstow Bridge on the Thames", "content_html": "<p><img alt=\"Godstow Bridge\" src=\"https://live.staticflickr.com/65535/54565326730_d73c161ebe_h_d.jpg\"></p>", "image": "https://photos.chrisjennings.net/assets/images/social/photos/Godstow Bridge.png", "date_modified": "2025-09-24T14:33:04+00:00", "authors": [], "tags": null}, {"id": "https://photos.chrisjennings.net/2022/ground-peak/", "url": "https://photos.chrisjennings.net/2022/ground-peak/", "title": "Ground Peak", "content_html": "<p><img alt=\"Ground Peak\" src=\"https://live.staticflickr.com/65535/51864255060_6385316a12_h_d.jpg\"></p>\n<ul>\n<li>Ground Up</li>\n<li>Asphalt Smoothed</li>\n<li>Dark Paved</li>\n</ul>", "image": "https://photos.chrisjennings.net/assets/images/social/photos/Ground Peak.png", "date_modified": "2025-09-24T14:33:04+00:00", "authors": [], "tags": null}, {"id": "https://photos.chrisjennings.net/2021/hay-bale-transporters/", "url": "https://photos.chrisjennings.net/2021/hay-bale-transporters/", "title": "Hay bale transporters", "content_html": "<p><img alt=\"Rusty trailers\" src=\"https://www.chrisjennings.net/uploads/91841238-4546-4ed5-979f-1ef40f28293a.jpeg\"></p>\n<p>Nothing to bale, but these trailers are queued up ready.</p>", "image": "https://photos.chrisjennings.net/assets/images/social/photos/Hay bale transporters.png", "date_modified": "2025-09-24T14:33:04+00:00", "authors": [], "tags": null}]}